[
  {
    "algorithm": "PPO",
    "map_name": "AI Training #5",
    "reward_mode": "delta_finished_progress_time_crashes",
    "reward_scalar_formula": "1000*finished + 100*progress_norm - 10*time_norm - 1*crashes",
    "reward_is_delta_potential": true,
    "action_layout": "gas_brake_steer",
    "strict_full_action_layout": true,
    "action_layout_policy": "strict_full_control_no_simplified_action_space",
    "env_max_time": 30.0,
    "episodes": 1000,
    "total_timesteps": 3500000,
    "max_runtime_minutes": 0.0,
    "collision_mode": "lidar",
    "collision_distance_threshold": 2.0,
    "lidar_mode": "aabb_clearance",
    "vehicle_hitbox": {
      "half_width": 1.1,
      "front_half_length": 2.15,
      "rear_half_length": 1.95,
      "half_height": 0.6,
      "safety_margin": 1,
      "source": "empirical_mesh_and_supervised_aabb_20260503"
    },
    "vertical_mode": false,
    "multi_surface_mode": false,
    "binary_gas_brake": true,
    "physics_tick_profile": "fixed100",
    "physics_tick_probs": null,
    "legacy_fixed_fps": null,
    "progress_metric_version": "progress_is_continuous_v20260505",
    "sb3_entrypoint": "PPO, SAC and TD3 from Stable-Baselines3 over local TM2D",
    "seed": 2026050508,
    "learning_rate": 0.0003,
    "buffer_size": 300000,
    "learning_starts": 1000,
    "batch_size": 256,
    "gamma": 0.9995,
    "tau": 0.005,
    "gradient_steps": 1,
    "train_freq": [
      1,
      "episode"
    ],
    "episode_update_policy": "ppo_rollout_update_approx_one_episode_n_steps_3000",
    "ent_coef": "0.01",
    "n_steps": 3000,
    "n_epochs": 10,
    "gae_lambda": 0.95,
    "clip_range": 0.2,
    "action_noise_sigma": 0.1,
    "net_arch": [
      32,
      16
    ],
    "activation_fn": "relu",
    "terminal_fitness_scale": 1000000.0,
    "pace_target_time": null,
    "initial_model_path": null,
    "observation_space": "Box([ 0.  0.  0.  0.  0.  0.  0.  0.  0.  0.  0.  0.  0.  0.  0. -1. -1. -1.\n -1. -1. -1. -1. -1. -1.  0.  0. -1. -1. -1. -1. -1. -1. -1. -1.], 1.0, (34,), float32)",
    "action_space": "Box([ 0.  0. -1.], 1.0, (3,), float32)",
    "physics": {
      "dt_ref": 0.01,
      "physics_tick_profile": "fixed100",
      "physics_tick_values": [
        1
      ],
      "physics_tick_probabilities": [
        1.0
      ],
      "max_speed": 130.0,
      "reverse_speed": 10.0,
      "gas_accel": 22.0,
      "brake_accel": 17.463,
      "drag": 0.1439,
      "rolling_drag": 5.549,
      "lateral_grip": 5.5,
      "max_yaw_rate": 1.5,
      "car_length": 4.8,
      "car_width": 2.6
    },
    "progress_bucket": 2.857142857142857
  },
  {
    "algorithm": "PPO",
    "map_name": "AI Training #5",
    "reward_mode": "delta_finished_progress_time_crashes",
    "reward_scalar_formula": "1000*finished + 100*progress_norm - 10*time_norm - 1*crashes",
    "reward_is_delta_potential": true,
    "action_layout": "gas_brake_steer",
    "strict_full_action_layout": true,
    "action_layout_policy": "strict_full_control_no_simplified_action_space",
    "env_max_time": 30.0,
    "episodes": 1000,
    "total_timesteps": 3500000,
    "max_runtime_minutes": 0.0,
    "collision_mode": "lidar",
    "collision_distance_threshold": 2.0,
    "lidar_mode": "aabb_clearance",
    "vehicle_hitbox": {
      "half_width": 1.1,
      "front_half_length": 2.15,
      "rear_half_length": 1.95,
      "half_height": 0.6,
      "safety_margin": 1,
      "source": "empirical_mesh_and_supervised_aabb_20260503"
    },
    "vertical_mode": false,
    "multi_surface_mode": false,
    "binary_gas_brake": true,
    "physics_tick_profile": "supervised_v2d",
    "physics_tick_probs": null,
    "legacy_fixed_fps": null,
    "progress_metric_version": "progress_is_continuous_v20260505",
    "sb3_entrypoint": "PPO, SAC and TD3 from Stable-Baselines3 over local TM2D",
    "seed": 2026050508,
    "learning_rate": 0.0003,
    "buffer_size": 300000,
    "learning_starts": 1000,
    "batch_size": 256,
    "gamma": 0.9995,
    "tau": 0.005,
    "gradient_steps": 1,
    "train_freq": [
      1,
      "episode"
    ],
    "episode_update_policy": "ppo_rollout_update_approx_one_episode_n_steps_3000",
    "ent_coef": "0.01",
    "n_steps": 3000,
    "n_epochs": 10,
    "gae_lambda": 0.95,
    "clip_range": 0.2,
    "action_noise_sigma": 0.1,
    "net_arch": [
      32,
      16
    ],
    "activation_fn": "relu",
    "terminal_fitness_scale": 1000000.0,
    "pace_target_time": null,
    "initial_model_path": null,
    "observation_space": "Box([ 0.  0.  0.  0.  0.  0.  0.  0.  0.  0.  0.  0.  0.  0.  0. -1. -1. -1.\n -1. -1. -1. -1. -1. -1.  0.  0. -1. -1. -1. -1. -1. -1. -1. -1.], 1.0, (34,), float32)",
    "action_space": "Box([ 0.  0. -1.], 1.0, (3,), float32)",
    "physics": {
      "dt_ref": 0.01,
      "physics_tick_profile": "supervised_v2d",
      "physics_tick_values": [
        1,
        2,
        3,
        4
      ],
      "physics_tick_probabilities": [
        0.938285,
        0.060381,
        0.000562,
        0.000772
      ],
      "max_speed": 130.0,
      "reverse_speed": 10.0,
      "gas_accel": 22.0,
      "brake_accel": 17.463,
      "drag": 0.1439,
      "rolling_drag": 5.549,
      "lateral_grip": 5.5,
      "max_yaw_rate": 1.5,
      "car_length": 4.8,
      "car_width": 2.6
    },
    "progress_bucket": 2.857142857142857
  },
  {
    "algorithm": "SAC",
    "map_name": "AI Training #5",
    "reward_mode": "delta_finished_progress_time_crashes",
    "reward_scalar_formula": "1000*finished + 100*progress_norm - 10*time_norm - 1*crashes",
    "reward_is_delta_potential": true,
    "action_layout": "gas_brake_steer",
    "strict_full_action_layout": true,
    "action_layout_policy": "strict_full_control_no_simplified_action_space",
    "env_max_time": 30.0,
    "episodes": 1000,
    "total_timesteps": 3500000,
    "max_runtime_minutes": 0.0,
    "collision_mode": "lidar",
    "collision_distance_threshold": 2.0,
    "lidar_mode": "aabb_clearance",
    "vehicle_hitbox": {
      "half_width": 1.1,
      "front_half_length": 2.15,
      "rear_half_length": 1.95,
      "half_height": 0.6,
      "safety_margin": 1,
      "source": "empirical_mesh_and_supervised_aabb_20260503"
    },
    "vertical_mode": false,
    "multi_surface_mode": false,
    "binary_gas_brake": true,
    "physics_tick_profile": "fixed100",
    "physics_tick_probs": null,
    "legacy_fixed_fps": null,
    "progress_metric_version": "progress_is_continuous_v20260505",
    "sb3_entrypoint": "PPO, SAC and TD3 from Stable-Baselines3 over local TM2D",
    "seed": 2026050508,
    "learning_rate": 0.0003,
    "buffer_size": 300000,
    "learning_starts": 1000,
    "batch_size": 256,
    "gamma": 0.9995,
    "tau": 0.005,
    "gradient_steps": 1,
    "train_freq": [
      1,
      "episode"
    ],
    "episode_update_policy": "off_policy_train_after_each_episode",
    "ent_coef": "0.01",
    "n_steps": 3000,
    "n_epochs": 10,
    "gae_lambda": 0.95,
    "clip_range": 0.2,
    "action_noise_sigma": 0.1,
    "net_arch": [
      32,
      16
    ],
    "activation_fn": "relu",
    "terminal_fitness_scale": 1000000.0,
    "pace_target_time": null,
    "initial_model_path": null,
    "observation_space": "Box([ 0.  0.  0.  0.  0.  0.  0.  0.  0.  0.  0.  0.  0.  0.  0. -1. -1. -1.\n -1. -1. -1. -1. -1. -1.  0.  0. -1. -1. -1. -1. -1. -1. -1. -1.], 1.0, (34,), float32)",
    "action_space": "Box([ 0.  0. -1.], 1.0, (3,), float32)",
    "physics": {
      "dt_ref": 0.01,
      "physics_tick_profile": "fixed100",
      "physics_tick_values": [
        1
      ],
      "physics_tick_probabilities": [
        1.0
      ],
      "max_speed": 130.0,
      "reverse_speed": 10.0,
      "gas_accel": 22.0,
      "brake_accel": 17.463,
      "drag": 0.1439,
      "rolling_drag": 5.549,
      "lateral_grip": 5.5,
      "max_yaw_rate": 1.5,
      "car_length": 4.8,
      "car_width": 2.6
    },
    "progress_bucket": 2.857142857142857
  },
  {
    "algorithm": "SAC",
    "map_name": "AI Training #5",
    "reward_mode": "delta_finished_progress_time_crashes",
    "reward_scalar_formula": "1000*finished + 100*progress_norm - 10*time_norm - 1*crashes",
    "reward_is_delta_potential": true,
    "action_layout": "gas_brake_steer",
    "strict_full_action_layout": true,
    "action_layout_policy": "strict_full_control_no_simplified_action_space",
    "env_max_time": 30.0,
    "episodes": 1000,
    "total_timesteps": 3500000,
    "max_runtime_minutes": 0.0,
    "collision_mode": "lidar",
    "collision_distance_threshold": 2.0,
    "lidar_mode": "aabb_clearance",
    "vehicle_hitbox": {
      "half_width": 1.1,
      "front_half_length": 2.15,
      "rear_half_length": 1.95,
      "half_height": 0.6,
      "safety_margin": 1,
      "source": "empirical_mesh_and_supervised_aabb_20260503"
    },
    "vertical_mode": false,
    "multi_surface_mode": false,
    "binary_gas_brake": true,
    "physics_tick_profile": "supervised_v2d",
    "physics_tick_probs": null,
    "legacy_fixed_fps": null,
    "progress_metric_version": "progress_is_continuous_v20260505",
    "sb3_entrypoint": "PPO, SAC and TD3 from Stable-Baselines3 over local TM2D",
    "seed": 2026050508,
    "learning_rate": 0.0003,
    "buffer_size": 300000,
    "learning_starts": 1000,
    "batch_size": 256,
    "gamma": 0.9995,
    "tau": 0.005,
    "gradient_steps": 1,
    "train_freq": [
      1,
      "episode"
    ],
    "episode_update_policy": "off_policy_train_after_each_episode",
    "ent_coef": "0.01",
    "n_steps": 3000,
    "n_epochs": 10,
    "gae_lambda": 0.95,
    "clip_range": 0.2,
    "action_noise_sigma": 0.1,
    "net_arch": [
      32,
      16
    ],
    "activation_fn": "relu",
    "terminal_fitness_scale": 1000000.0,
    "pace_target_time": null,
    "initial_model_path": null,
    "observation_space": "Box([ 0.  0.  0.  0.  0.  0.  0.  0.  0.  0.  0.  0.  0.  0.  0. -1. -1. -1.\n -1. -1. -1. -1. -1. -1.  0.  0. -1. -1. -1. -1. -1. -1. -1. -1.], 1.0, (34,), float32)",
    "action_space": "Box([ 0.  0. -1.], 1.0, (3,), float32)",
    "physics": {
      "dt_ref": 0.01,
      "physics_tick_profile": "supervised_v2d",
      "physics_tick_values": [
        1,
        2,
        3,
        4
      ],
      "physics_tick_probabilities": [
        0.938285,
        0.060381,
        0.000562,
        0.000772
      ],
      "max_speed": 130.0,
      "reverse_speed": 10.0,
      "gas_accel": 22.0,
      "brake_accel": 17.463,
      "drag": 0.1439,
      "rolling_drag": 5.549,
      "lateral_grip": 5.5,
      "max_yaw_rate": 1.5,
      "car_length": 4.8,
      "car_width": 2.6
    },
    "progress_bucket": 2.857142857142857
  },
  {
    "algorithm": "TD3",
    "map_name": "AI Training #5",
    "reward_mode": "delta_finished_progress_time_crashes",
    "reward_scalar_formula": "1000*finished + 100*progress_norm - 10*time_norm - 1*crashes",
    "reward_is_delta_potential": true,
    "action_layout": "gas_brake_steer",
    "strict_full_action_layout": true,
    "action_layout_policy": "strict_full_control_no_simplified_action_space",
    "env_max_time": 30.0,
    "episodes": 1000,
    "total_timesteps": 3500000,
    "max_runtime_minutes": 0.0,
    "collision_mode": "lidar",
    "collision_distance_threshold": 2.0,
    "lidar_mode": "aabb_clearance",
    "vehicle_hitbox": {
      "half_width": 1.1,
      "front_half_length": 2.15,
      "rear_half_length": 1.95,
      "half_height": 0.6,
      "safety_margin": 1,
      "source": "empirical_mesh_and_supervised_aabb_20260503"
    },
    "vertical_mode": false,
    "multi_surface_mode": false,
    "binary_gas_brake": true,
    "physics_tick_profile": "fixed100",
    "physics_tick_probs": null,
    "legacy_fixed_fps": null,
    "progress_metric_version": "progress_is_continuous_v20260505",
    "sb3_entrypoint": "PPO, SAC and TD3 from Stable-Baselines3 over local TM2D",
    "seed": 2026050508,
    "learning_rate": 0.0003,
    "buffer_size": 300000,
    "learning_starts": 1000,
    "batch_size": 256,
    "gamma": 0.9995,
    "tau": 0.005,
    "gradient_steps": 1,
    "train_freq": [
      1,
      "episode"
    ],
    "episode_update_policy": "off_policy_train_after_each_episode",
    "ent_coef": "0.01",
    "n_steps": 3000,
    "n_epochs": 10,
    "gae_lambda": 0.95,
    "clip_range": 0.2,
    "action_noise_sigma": 0.1,
    "net_arch": [
      32,
      16
    ],
    "activation_fn": "relu",
    "terminal_fitness_scale": 1000000.0,
    "pace_target_time": null,
    "initial_model_path": null,
    "observation_space": "Box([ 0.  0.  0.  0.  0.  0.  0.  0.  0.  0.  0.  0.  0.  0.  0. -1. -1. -1.\n -1. -1. -1. -1. -1. -1.  0.  0. -1. -1. -1. -1. -1. -1. -1. -1.], 1.0, (34,), float32)",
    "action_space": "Box([ 0.  0. -1.], 1.0, (3,), float32)",
    "physics": {
      "dt_ref": 0.01,
      "physics_tick_profile": "fixed100",
      "physics_tick_values": [
        1
      ],
      "physics_tick_probabilities": [
        1.0
      ],
      "max_speed": 130.0,
      "reverse_speed": 10.0,
      "gas_accel": 22.0,
      "brake_accel": 17.463,
      "drag": 0.1439,
      "rolling_drag": 5.549,
      "lateral_grip": 5.5,
      "max_yaw_rate": 1.5,
      "car_length": 4.8,
      "car_width": 2.6
    },
    "progress_bucket": 2.857142857142857
  },
  {
    "algorithm": "TD3",
    "map_name": "AI Training #5",
    "reward_mode": "delta_finished_progress_time_crashes",
    "reward_scalar_formula": "1000*finished + 100*progress_norm - 10*time_norm - 1*crashes",
    "reward_is_delta_potential": true,
    "action_layout": "gas_brake_steer",
    "strict_full_action_layout": true,
    "action_layout_policy": "strict_full_control_no_simplified_action_space",
    "env_max_time": 30.0,
    "episodes": 1000,
    "total_timesteps": 3500000,
    "max_runtime_minutes": 0.0,
    "collision_mode": "lidar",
    "collision_distance_threshold": 2.0,
    "lidar_mode": "aabb_clearance",
    "vehicle_hitbox": {
      "half_width": 1.1,
      "front_half_length": 2.15,
      "rear_half_length": 1.95,
      "half_height": 0.6,
      "safety_margin": 1,
      "source": "empirical_mesh_and_supervised_aabb_20260503"
    },
    "vertical_mode": false,
    "multi_surface_mode": false,
    "binary_gas_brake": true,
    "physics_tick_profile": "supervised_v2d",
    "physics_tick_probs": null,
    "legacy_fixed_fps": null,
    "progress_metric_version": "progress_is_continuous_v20260505",
    "sb3_entrypoint": "PPO, SAC and TD3 from Stable-Baselines3 over local TM2D",
    "seed": 2026050508,
    "learning_rate": 0.0003,
    "buffer_size": 300000,
    "learning_starts": 1000,
    "batch_size": 256,
    "gamma": 0.9995,
    "tau": 0.005,
    "gradient_steps": 1,
    "train_freq": [
      1,
      "episode"
    ],
    "episode_update_policy": "off_policy_train_after_each_episode",
    "ent_coef": "0.01",
    "n_steps": 3000,
    "n_epochs": 10,
    "gae_lambda": 0.95,
    "clip_range": 0.2,
    "action_noise_sigma": 0.1,
    "net_arch": [
      32,
      16
    ],
    "activation_fn": "relu",
    "terminal_fitness_scale": 1000000.0,
    "pace_target_time": null,
    "initial_model_path": null,
    "observation_space": "Box([ 0.  0.  0.  0.  0.  0.  0.  0.  0.  0.  0.  0.  0.  0.  0. -1. -1. -1.\n -1. -1. -1. -1. -1. -1.  0.  0. -1. -1. -1. -1. -1. -1. -1. -1.], 1.0, (34,), float32)",
    "action_space": "Box([ 0.  0. -1.], 1.0, (3,), float32)",
    "physics": {
      "dt_ref": 0.01,
      "physics_tick_profile": "supervised_v2d",
      "physics_tick_values": [
        1,
        2,
        3,
        4
      ],
      "physics_tick_probabilities": [
        0.938285,
        0.060381,
        0.000562,
        0.000772
      ],
      "max_speed": 130.0,
      "reverse_speed": 10.0,
      "gas_accel": 22.0,
      "brake_accel": 17.463,
      "drag": 0.1439,
      "rolling_drag": 5.549,
      "lateral_grip": 5.5,
      "max_yaw_rate": 1.5,
      "car_length": 4.8,
      "car_width": 2.6
    },
    "progress_bucket": 2.857142857142857
  }
]